<?xml version="1.0" encoding="UTF-8"?><record_update table="ua_table_licensing_config">
    <ua_table_licensing_config action="INSERT_OR_UPDATE">
        <is_fulfillment>false</is_fulfillment>
        <license_condition/>
        <license_model>none</license_model>
        <license_roles/>
        <name>x_1559885_powersys_power_server</name>
        <op_delete>true</op_delete>
        <op_insert>true</op_insert>
        <op_update>true</op_update>
        <owner_condition/>
        <sys_class_name>ua_table_licensing_config</sys_class_name>
        <sys_created_by>admin</sys_created_by>
        <sys_created_on>2024-11-28 06:36:22</sys_created_on>
        <sys_id>40272e03530a1a10938e55e0a0490e24</sys_id>
        <sys_mod_count>0</sys_mod_count>
        <sys_name>x_1559885_powersys_power_server</sys_name>
        <sys_package display_value="Power System" source="x_1559885_powersys">e434ee0353c61a10938e55e0a0490e01</sys_package>
        <sys_policy/>
        <sys_scope display_value="Power System">e434ee0353c61a10938e55e0a0490e01</sys_scope>
        <sys_update_name>ua_table_licensing_config_40272e03530a1a10938e55e0a0490e24</sys_update_name>
        <sys_updated_by>admin</sys_updated_by>
        <sys_updated_on>2024-11-28 06:36:22</sys_updated_on>
    </ua_table_licensing_config>
</record_update>
